setup.py
backproof_sdk/__init__.py
backproof_sdk.egg-info/PKG-INFO
backproof_sdk.egg-info/SOURCES.txt
backproof_sdk.egg-info/dependency_links.txt
backproof_sdk.egg-info/top_level.txt