Metadata-Version: 2.1
Name: backproof-sdk
Version: 0.1.0
Summary: Python SDK for Backproof
Author: Thomas Nicollet <thomas.nicollet@nebulis.io>
License: UNKNOWN
Platform: UNKNOWN
